{
  "generated_at": "2026-06-29T16:32:59.169151+00:00",
  "generated_at_hkt": "2026-06-30 00:32 HKT",
  "indices": {
    "HK": {
      "label": "Hong Kong",
      "flag": "🇭🇰",
      "primary": {
        "name": "HSI",
        "ticker": "^HSI",
        "close": 22671.86,
        "pct_change": -1.76,
        "volume_fmt": "HK$4.2B"
      },
      "secondary": {
        "name": "HSCEI",
        "ticker": "^HSCE",
        "close": 7460.84,
        "pct_change": -1.94,
        "volume_fmt": "HK$0.0B"
      },
      "sparkline": [
        23336.28,
        23412.18,
        23076.91,
        22671.86
      ]
    },
    "CN": {
      "label": "China A",
      "flag": "🇨🇳",
      "primary": {
        "name": "CSI 300",
        "ticker": "000300.SS",
        "close": NaN,
        "pct_change": NaN,
        "volume_fmt": "¥0.0T"
      },
      "secondary": {
        "name": "SSE Composite",
        "ticker": "000001.SS",
        "close": NaN,
        "pct_change": NaN,
        "volume_fmt": "¥0.0T"
      },
      "sparkline": [
        4919.39,
        4943.02,
        5020.1,
        4868.22,
        NaN
      ]
    },
    "KR": {
      "label": "Korea",
      "flag": "🇰🇷",
      "primary": {
        "name": "KOSPI",
        "ticker": "^KS11",
        "close": NaN,
        "pct_change": NaN,
        "volume_fmt": "₩0.0T"
      },
      "secondary": {
        "name": "KOSDAQ",
        "ticker": "^KQ11",
        "close": NaN,
        "pct_change": NaN,
        "volume_fmt": "₩0.0T"
      },
      "sparkline": [
        8203.84,
        8471.02,
        8930.3,
        8411.21,
        NaN
      ]
    },
    "JP": {
      "label": "Japan",
      "flag": "🇯🇵",
      "primary": {
        "name": "Nikkei 225",
        "ticker": "^N225",
        "close": 69360.88,
        "pct_change": -4.15,
        "volume_fmt": "¥0.0T"
      },
      "secondary": {
        "name": "TOPIX",
        "ticker": "^TPX",
        "close": null,
        "pct_change": null,
        "volume_fmt": "¥0.0T"
      },
      "sparkline": [
        69788.38,
        69174.97,
        72366.34,
        69360.88
      ]
    },
    "US": {
      "label": "US",
      "flag": "🇺🇸",
      "primary": {
        "name": "S&P 500",
        "ticker": "^GSPC",
        "close": 7410.07,
        "pct_change": 0.76,
        "volume_fmt": "$1.4B"
      },
      "secondary": {
        "name": "NASDAQ",
        "ticker": "^IXIC",
        "close": 25622.3,
        "pct_change": 1.28,
        "volume_fmt": "$4.7B"
      },
      "tertiary": {
        "name": "Dow Jones",
        "ticker": "^DJI",
        "close": 52100.06,
        "pct_change": 0.43,
        "volume_fmt": "$0.3B"
      },
      "sparkline": [
        7365.46,
        7358.22,
        7357.49,
        7354.02,
        7410.07
      ]
    }
  },
  "sectors": {
    "AI / Chips": {
      "anchor": "SOXX",
      "markets": "US/HK/KR",
      "close": 605.91,
      "pct_change": 2.71
    },
    "CN Internet": {
      "anchor": "KWEB",
      "markets": "HK/CN",
      "close": 24.22,
      "pct_change": 1.15
    },
    "EV / Battery": {
      "anchor": "LIT",
      "markets": "CN/US",
      "close": 76.85,
      "pct_change": 1.21
    },
    "Robotics": {
      "anchor": "ROBO",
      "markets": "JP/CN",
      "close": 82.67,
      "pct_change": 0.82
    },
    "Clean Energy": {
      "anchor": "ICLN",
      "markets": "US/CN",
      "close": 19.76,
      "pct_change": 1.33
    },
    "Biotech": {
      "anchor": "XBI",
      "markets": "US/HK/KR",
      "close": 156.31,
      "pct_change": 0.6
    },
    "Financials": {
      "anchor": "XLF",
      "markets": "US/HK/KR",
      "close": 53.74,
      "pct_change": 0.31
    },
    "Defence": {
      "anchor": "ITA",
      "markets": "US/KR",
      "close": 239.09,
      "pct_change": 0.97
    }
  },
  "fx": {
    "USD/HKD": {
      "rate": 7.84,
      "pct_change": 0.04
    },
    "USD/CNY": {
      "rate": 6.79,
      "pct_change": -0.07
    },
    "USD/KRW": {
      "rate": 1542.26,
      "pct_change": -0.27
    },
    "USD/JPY": {
      "rate": 161.94,
      "pct_change": 0.08
    },
    "EUR/USD": {
      "rate": 1.14,
      "pct_change": 0.59
    },
    "DXY": {
      "rate": 101.12,
      "pct_change": -0.23
    }
  },
  "movers": {
    "HK": {
      "gainers": [],
      "losers": [],
      "is_friday_fallback": false,
      "screener_note": "Last trading day data"
    },
    "US": {
      "gainers": [
        {
          "ticker": "AMAT",
          "close": 700.14,
          "pct_change": 11.69,
          "volume": 7317095,
          "volume_fmt": "$7M",
          "longName": "Applied Materials, Inc.",
          "industry": "Semiconductor Equipment & Materials"
        },
        {
          "ticker": "KLAC",
          "close": 271.89,
          "pct_change": 9.35,
          "volume": 6155401,
          "volume_fmt": "$6M",
          "longName": "KLA Corporation",
          "industry": "Semiconductor Equipment & Materials"
        },
        {
          "ticker": "LRCX",
          "close": 410.6,
          "pct_change": 8.31,
          "volume": 6692201,
          "volume_fmt": "$7M",
          "longName": "Lam Research Corporation",
          "industry": "Semiconductor Equipment & Materials"
        },
        {
          "ticker": "PANW",
          "close": 329.1,
          "pct_change": 8.18,
          "volume": 4730765,
          "volume_fmt": "$5M",
          "longName": "Palo Alto Networks, Inc.",
          "industry": "Software - Infrastructure"
        },
        {
          "ticker": "CRWD",
          "close": 747.67,
          "pct_change": 6.64,
          "volume": 2594160,
          "volume_fmt": "$3M",
          "longName": "CrowdStrike Holdings, Inc.",
          "industry": "Software - Infrastructure"
        }
      ],
      "losers": [
        {
          "ticker": "HON",
          "close": 235.35,
          "pct_change": -49.32,
          "volume": 2904775,
          "volume_fmt": "$3M",
          "longName": "Honeywell International Inc.",
          "industry": "Conglomerates"
        },
        {
          "ticker": "ACN",
          "close": 125.3,
          "pct_change": -2.85,
          "volume": 5450215,
          "volume_fmt": "$5M",
          "longName": "Accenture plc",
          "industry": "Information Technology Services"
        },
        {
          "ticker": "MU",
          "close": 1106.14,
          "pct_change": -2.31,
          "volume": 35637975,
          "volume_fmt": "$36M",
          "longName": "Micron Technology, Inc.",
          "industry": "Semiconductors"
        },
        {
          "ticker": "TMO",
          "close": 502.19,
          "pct_change": -2.11,
          "volume": 663707,
          "volume_fmt": "663,707",
          "longName": "Thermo Fisher Scientific Inc.",
          "industry": "Diagnostics & Research"
        },
        {
          "ticker": "SMCI",
          "close": 29.99,
          "pct_change": -2.09,
          "volume": 20178911,
          "volume_fmt": "$20M",
          "longName": "Super Micro Computer, Inc.",
          "industry": "Computer Hardware"
        }
      ],
      "is_friday_fallback": false,
      "screener_note": "Last trading day data"
    }
  },
  "news": [
    {
      "title": "Alphabet joins Dow Jones Industrial Average, replacing Verizon",
      "url": "https://qz.com/alphabet-joins-dow-jones-industrial-average-verizon-062926?.tsrc=rss",
      "source": "Yahoo! Finance: ^GSPC News",
      "published_hkt": "2026-06-30 00:29 HKT",
      "label": "US Markets"
    },
    {
      "title": "Why Vertex Stock Is Rising Today",
      "url": "https://www.fool.com/investing/2026/06/29/why-vertex-stock-is-rising-today/?.tsrc=rss",
      "source": "Yahoo! Finance: NVDA News",
      "published_hkt": "2026-06-30 00:21 HKT",
      "label": "Semiconductors"
    },
    {
      "title": "Update: Communication Services, Consumer Discretionary Help Push US Equity Indexes Higher",
      "url": "https://finance.yahoo.com/markets/world-indices/articles/communication-services-consumer-discretionary-help-162054928.html?.tsrc=rss",
      "source": "Yahoo! Finance: ^GSPC News",
      "published_hkt": "2026-06-30 00:20 HKT",
      "label": "US Markets"
    },
    {
      "title": "Here Are My Top \"Magnificent Seven\" Stocks to Buy Now",
      "url": "https://www.fool.com/investing/2026/06/29/here-are-my-top-magnificent-seven-stocks-to-buy-no/?.tsrc=rss",
      "source": "Yahoo! Finance: NVDA News",
      "published_hkt": "2026-06-30 00:20 HKT",
      "label": "Semiconductors"
    },
    {
      "title": "3 Reasons to Avoid ESNT and 1 Stock to Buy Instead",
      "url": "https://finance.yahoo.com/markets/stocks/articles/3-reasons-avoid-esnt-1-161815085.html?.tsrc=rss",
      "source": "Yahoo! Finance: ^GSPC News",
      "published_hkt": "2026-06-30 00:18 HKT",
      "label": "US Markets"
    },
    {
      "title": "Axon Soars on Trump Stock Purchase Highlighting Insider Trading Issues",
      "url": "https://247wallst.com/investing/2026/06/29/axon-soars-on-trump-stock-purchase-highlighting-insider-trading-issues/?.tsrc=rss",
      "source": "Yahoo! Finance: NVDA News",
      "published_hkt": "2026-06-30 00:13 HKT",
      "label": "Semiconductors"
    },
    {
      "title": "Why Is NNBR Stock Rising Today?",
      "url": "https://stocktwits.com/news-articles/markets/equity/why-is-nnbr-stock-rising-today-awards-nvidia-data-centers/cZ19WMER7L4?.tsrc=rss",
      "source": "Yahoo! Finance: NVDA News",
      "published_hkt": "2026-06-30 00:13 HKT",
      "label": "Semiconductors"
    },
    {
      "title": "BofA upgrades global growth forecast as AI boom accelerates: Chart of the Day",
      "url": "https://finance.yahoo.com/markets/article/bofa-upgrades-global-growth-forecast-as-ai-boom-accelerates-chart-of-the-day-161222422.html?.tsrc=rss",
      "source": "Yahoo! Finance: ^GSPC News",
      "published_hkt": "2026-06-30 00:12 HKT",
      "label": "US Markets"
    },
    {
      "title": "Archer Aviation Stock Hits a New 52-Week Low. Is Now the Time to Buy?",
      "url": "https://www.fool.com/investing/2026/06/29/archer-aviation-stock-hits-a-new-52-week-low-is-no/?.tsrc=rss",
      "source": "Yahoo! Finance: NVDA News",
      "published_hkt": "2026-06-30 00:12 HKT",
      "label": "Semiconductors"
    },
    {
      "title": "3 Reasons to Sell DAL and 1 Stock to Buy Instead",
      "url": "https://finance.yahoo.com/markets/stocks/articles/3-reasons-sell-dal-1-161015360.html?.tsrc=rss",
      "source": "Yahoo! Finance: ^GSPC News",
      "published_hkt": "2026-06-30 00:10 HKT",
      "label": "US Markets"
    },
    {
      "title": "Telecom Turmoil: Comcast Rises 7% on Media Spinoff, AT&T Falls 5% on CFO Exit and Starlink Threat, Verizon Sinks 7% on Dow Exit",
      "url": "https://247wallst.com/investing/2026/06/29/telecom-turmoil-comcast-rises-7-on-media-spinoff-att-falls-5-on-cfo-exit-and-starlink-threat-verizon-sinks-7-on-dow-exit/?.tsrc=rss",
      "source": "Yahoo! Finance: NVDA News",
      "published_hkt": "2026-06-30 00:04 HKT",
      "label": "Semiconductors"
    },
    {
      "title": "iShares Fund Face-off: Is the Russell 2000 Growth ETF or Morningstar Small-Cap Growth ETF the Better Buy?",
      "url": "https://www.fool.com/coverage/etfs/2026/06/29/ishares-fund-face-off-is-the-russell-2000-growth-etf-or-morningstar-small-cap-growth-etf-the-better-buy/?.tsrc=rss",
      "source": "Yahoo! Finance: ^GSPC News",
      "published_hkt": "2026-06-30 00:04 HKT",
      "label": "US Markets"
    },
    {
      "title": "3 No-Brainer Dividend Stocks to Buy Right Now",
      "url": "https://www.fool.com/investing/2026/06/29/x-no-brainer-dividend-stocks-to-buy-right-now/?.tsrc=rss",
      "source": "Yahoo! Finance: ^GSPC News",
      "published_hkt": "2026-06-30 00:03 HKT",
      "label": "US Markets"
    },
    {
      "title": "Globe Life (GL): Buy, Sell, or Hold Post Q1 Earnings?",
      "url": "https://finance.yahoo.com/markets/stocks/articles/globe-life-gl-buy-sell-155415990.html?.tsrc=rss",
      "source": "Yahoo! Finance: ^GSPC News",
      "published_hkt": "2026-06-29 23:54 HKT",
      "label": "US Markets"
    },
    {
      "title": "港股通盈富基金淨流出73.46億港元",
      "url": "https://hk.finance.yahoo.com/news/%E6%B8%AF%E8%82%A1%E9%80%9A%E7%9B%88%E5%AF%8C%E5%9F%BA%E9%87%91%E6%B7%A8%E6%B5%81%E5%87%BA73-46%E5%84%84%E6%B8%AF%E5%85%83-102501521.html?.tsrc=rss",
      "source": "Yahoo! Finance: 9988.HK News",
      "published_hkt": "2026-06-29 18:25 HKT",
      "label": "China Tech"
    },
    {
      "title": "中國機器人賽道新增兩家獨角獸 行業融資勢頭保持強勁",
      "url": "https://hk.finance.yahoo.com/news/%E4%B8%AD%E5%9C%8B%E6%A9%9F%E5%99%A8%E4%BA%BA%E8%B3%BD%E9%81%93%E6%96%B0%E5%A2%9E%E5%85%A9%E5%AE%B6%E7%8D%A8%E8%A7%92%E7%8D%B8-%E8%A1%8C%E6%A5%AD%E8%9E%8D%E8%B3%87%E5%8B%A2%E9%A0%AD%E4%BF%9D%E6%8C%81%E5%BC%B7%E5%8B%81-100227877.html?.tsrc=rss",
      "source": "Yahoo! Finance: 9988.HK News",
      "published_hkt": "2026-06-29 18:02 HKT",
      "label": "China Tech"
    },
    {
      "title": "〈港股盤後〉恒指強勢反彈收復兩萬三關口 創新藥與半導體領漲",
      "url": "https://hk.finance.yahoo.com/news/%E6%B8%AF%E8%82%A1%E7%9B%A4%E5%BE%8C-%E6%81%92%E6%8C%87%E5%BC%B7%E5%8B%A2%E5%8F%8D%E5%BD%88%E6%94%B6%E5%BE%A9%E5%85%A9%E8%90%AC%E4%B8%89%E9%97%9C%E5%8F%A3-%E5%89%B5%E6%96%B0%E8%97%A5%E8%88%87%E5%8D%8A%E5%B0%8E%E9%AB%94%E9%A0%98%E6%BC%B2-083916685.html?.tsrc=rss",
      "source": "Yahoo! Finance: ^HSI News",
      "published_hkt": "2026-06-29 16:39 HKT",
      "label": "Asia Markets"
    },
    {
      "title": "《港股》恒指升354點收復二萬三關  網易及中芯升6%  醫藥股炒上  聯想逆市跌9%",
      "url": "https://hk.finance.yahoo.com/news/%E6%B8%AF%E8%82%A1-%E6%81%92%E6%8C%87%E5%8D%87354%E9%BB%9E%E6%94%B6%E5%BE%A9%E4%BA%8C%E8%90%AC%E4%B8%89%E9%97%9C-%E7%B6%B2%E6%98%93%E5%8F%8A%E4%B8%AD%E8%8A%AF%E5%8D%876-%E9%86%AB%E8%97%A5%E8%82%A1%E7%82%92%E4%B8%8A-%E8%81%AF%E6%83%B3%E9%80%86%E5%B8%82%E8%B7%8C9-082751376.html?.tsrc=rss",
      "source": "Yahoo! Finance: ^HSI News",
      "published_hkt": "2026-06-29 16:27 HKT",
      "label": "Asia Markets"
    },
    {
      "title": "恒指全日收報23026.68點  升 1.57%  成交3,153.79億元",
      "url": "https://hk.finance.yahoo.com/news/%E6%81%92%E6%8C%87%E5%85%A8%E6%97%A5%E6%94%B6%E5%A0%B123026-68%E9%BB%9E-%E5%8D%87-1-57-081500857.html?.tsrc=rss",
      "source": "Yahoo! Finance: ^HSI News",
      "published_hkt": "2026-06-29 16:15 HKT",
      "label": "Asia Markets"
    },
    {
      "title": "《全日速報》恆指升354點; 恆生科技指數升137點 美團升逾5% 阿里巴巴升逾3% 藥明康德、華虹宏力創新高 成交暢旺",
      "url": "https://hk.finance.yahoo.com/news/%E5%85%A8%E6%97%A5%E9%80%9F%E5%A0%B1-%E6%81%86%E6%8C%87%E5%8D%87354%E9%BB%9E-%E6%81%86%E7%94%9F%E7%A7%91%E6%8A%80%E6%8C%87%E6%95%B8%E5%8D%87137%E9%BB%9E-%E7%BE%8E%E5%9C%98%E5%8D%87%E9%80%BE5-%E9%98%BF%E9%87%8C%E5%B7%B4%E5%B7%B4%E5%8D%87%E9%80%BE3-081202333.html?.tsrc=rss",
      "source": "Yahoo! Finance: ^HSI News",
      "published_hkt": "2026-06-29 16:12 HKT",
      "label": "Asia Markets"
    },
    {
      "title": "《大行》摩通料網易(09999.HK)轉為雙重主要上市即獲納入滬港通  對股價屬正面影響",
      "url": "https://hk.finance.yahoo.com/news/%E5%A4%A7%E8%A1%8C-%E6%91%A9%E9%80%9A%E6%96%99%E7%B6%B2%E6%98%93-09999-hk-%E8%BD%89%E7%82%BA%E9%9B%99%E9%87%8D%E4%B8%BB%E8%A6%81%E4%B8%8A%E5%B8%82%E5%8D%B3%E7%8D%B2%E7%B4%8D%E5%85%A5%E6%BB%AC%E6%B8%AF%E9%80%9A-075152616.html?.tsrc=rss",
      "source": "Yahoo! Finance: ^HSI News",
      "published_hkt": "2026-06-29 15:51 HKT",
      "label": "Asia Markets"
    },
    {
      "title": "耀才植耀輝相信恒指在半年結後有機會重上25500-26000點水平",
      "url": "https://hk.finance.yahoo.com/news/%E8%80%80%E6%89%8D%E6%A4%8D%E8%80%80%E8%BC%9D%E7%9B%B8%E4%BF%A1%E6%81%92%E6%8C%87%E5%9C%A8%E5%8D%8A%E5%B9%B4%E7%B5%90%E5%BE%8C%E6%9C%89%E6%A9%9F%E6%9C%83%E9%87%8D%E4%B8%8A25500-26000%E9%BB%9E%E6%B0%B4%E5%B9%B3-065450685.html?.tsrc=rss",
      "source": "Yahoo! Finance: ^HSI News",
      "published_hkt": "2026-06-29 14:54 HKT",
      "label": "Asia Markets"
    },
    {
      "title": "全押算力伺服器PCB 廣合科技逆市突圍",
      "url": "https://hk.finance.yahoo.com/news/%E5%85%A8%E6%8A%BC%E7%AE%97%E5%8A%9B%E4%BC%BA%E6%9C%8D%E5%99%A8pcb-%E5%BB%A3%E5%90%88%E7%A7%91%E6%8A%80%E9%80%86%E5%B8%82%E7%AA%81%E5%9C%8D-063457870.html?.tsrc=rss",
      "source": "Yahoo! Finance: ^HSI News",
      "published_hkt": "2026-06-29 14:34 HKT",
      "label": "Asia Markets"
    },
    {
      "title": "百度股價飆升，旗下AI晶片子公司崑崙芯瞄準500億美元估值赴港上市",
      "url": "https://hk.finance.yahoo.com/news/%E7%99%BE%E5%BA%A6%E8%82%A1%E5%83%B9%E9%A3%86%E5%8D%87-%E6%97%97%E4%B8%8Bai%E6%99%B6%E7%89%87%E5%AD%90%E5%85%AC%E5%8F%B8%E5%B4%91%E5%B4%99%E8%8A%AF%E7%9E%84%E6%BA%96500%E5%84%84%E7%BE%8E%E5%85%83%E4%BC%B0%E5%80%BC%E8%B5%B4%E6%B8%AF%E4%B8%8A%E5%B8%82-062159847.html?.tsrc=rss",
      "source": "Yahoo! Finance: ^HSI News",
      "published_hkt": "2026-06-29 14:21 HKT",
      "label": "Asia Markets"
    },
    {
      "title": "《半日速報》恆指升482點; 恆生科技指數升156點 美團升逾7% 阿里巴巴升逾6% 騰訊升逾3% 藥明康德創新高",
      "url": "https://hk.finance.yahoo.com/news/%E5%8D%8A%E6%97%A5%E9%80%9F%E5%A0%B1-%E6%81%86%E6%8C%87%E5%8D%87482%E9%BB%9E-%E6%81%86%E7%94%9F%E7%A7%91%E6%8A%80%E6%8C%87%E6%95%B8%E5%8D%87156%E9%BB%9E-%E7%BE%8E%E5%9C%98%E5%8D%87%E9%80%BE7-%E9%98%BF%E9%87%8C%E5%B7%B4%E5%B7%B4%E5%8D%87%E9%80%BE6-041202102.html?.tsrc=rss",
      "source": "Yahoo! Finance: 9988.HK News",
      "published_hkt": "2026-06-29 12:12 HKT",
      "label": "China Tech"
    },
    {
      "title": "港股期結日盤中突破23000點    科指彈逾3%",
      "url": "https://hk.finance.yahoo.com/news/%E6%B8%AF%E8%82%A1%E6%9C%9F%E7%B5%90%E6%97%A5%E7%9B%A4%E4%B8%AD%E7%AA%81%E7%A0%B423000%E9%BB%9E-%E7%A7%91%E6%8C%87%E5%BD%88%E9%80%BE3-022806437.html?.tsrc=rss",
      "source": "Yahoo! Finance: 9988.HK News",
      "published_hkt": "2026-06-29 10:28 HKT",
      "label": "China Tech"
    },
    {
      "title": "港股期指結算日反彈曾見22960點     ATMJ齊彈、百度彈7%",
      "url": "https://hk.finance.yahoo.com/news/%E6%B8%AF%E8%82%A1%E6%9C%9F%E6%8C%87%E7%B5%90%E7%AE%97%E6%97%A5%E5%8F%8D%E5%BD%88%E6%9B%BE%E8%A6%8B22960%E9%BB%9E-atmj%E9%BD%8A%E5%BD%88-%E7%99%BE%E5%BA%A6%E5%BD%887-021346463.html?.tsrc=rss",
      "source": "Yahoo! Finance: 9988.HK News",
      "published_hkt": "2026-06-29 10:13 HKT",
      "label": "China Tech"
    },
    {
      "title": "《港股》恒指高開155點 網易升4% 阿里彈逾2%",
      "url": "https://hk.finance.yahoo.com/news/%E6%B8%AF%E8%82%A1-%E6%81%92%E6%8C%87%E9%AB%98%E9%96%8B155%E9%BB%9E-%E7%B6%B2%E6%98%93%E5%8D%874-%E9%98%BF%E9%87%8C%E5%BD%88%E9%80%BE2-012946201.html?.tsrc=rss",
      "source": "Yahoo! Finance: 9988.HK News",
      "published_hkt": "2026-06-29 09:29 HKT",
      "label": "China Tech"
    }
  ]
}