{
  "generated_at": "2026-06-09T17:52:09.814000+00:00",
  "generated_at_hkt": "2026-06-10 01:52 HKT",
  "indices": {
    "HK": {
      "label": "Hong Kong",
      "flag": "🇭🇰",
      "primary": {
        "name": "HSI",
        "ticker": "^HSI",
        "close": 24657.06,
        "pct_change": -1.22,
        "volume_fmt": "HK$3.8B"
      },
      "secondary": {
        "name": "HSCEI",
        "ticker": "^HSCE",
        "close": 8341.36,
        "pct_change": -1.13,
        "volume_fmt": "HK$0.0B"
      },
      "sparkline": [
        25633.21,
        25253.4,
        24961.95,
        24657.06
      ]
    },
    "CN": {
      "label": "China A",
      "flag": "🇨🇳",
      "primary": {
        "name": "CSI 300",
        "ticker": "000300.SS",
        "close": NaN,
        "pct_change": NaN,
        "volume_fmt": "¥0.0T"
      },
      "secondary": {
        "name": "SSE Composite",
        "ticker": "000001.SS",
        "close": NaN,
        "pct_change": NaN,
        "volume_fmt": "¥0.0T"
      },
      "sparkline": [
        4938.81,
        4904.75,
        4816.92,
        4713.64,
        NaN
      ]
    },
    "KR": {
      "label": "Korea",
      "flag": "🇰🇷",
      "primary": {
        "name": "KOSPI",
        "ticker": "^KS11",
        "close": 7484.41,
        "pct_change": -8.29,
        "volume_fmt": "₩0.0T"
      },
      "secondary": {
        "name": "KOSDAQ",
        "ticker": "^KQ11",
        "close": 911.39,
        "pct_change": -9.08,
        "volume_fmt": "₩0.0T"
      },
      "sparkline": [
        8801.49,
        8639.41,
        8160.59,
        7484.41
      ]
    },
    "JP": {
      "label": "Japan",
      "flag": "🇯🇵",
      "primary": {
        "name": "Nikkei 225",
        "ticker": "^N225",
        "close": 64024.6,
        "pct_change": -3.85,
        "volume_fmt": "¥0.0T"
      },
      "secondary": {
        "name": "TOPIX",
        "ticker": "^TPX",
        "close": null,
        "pct_change": null,
        "volume_fmt": "¥0.0T"
      },
      "sparkline": [
        68402.13,
        67470.69,
        66588.12,
        64024.6
      ]
    },
    "US": {
      "label": "US",
      "flag": "🇺🇸",
      "primary": {
        "name": "S&P 500",
        "ticker": "^GSPC",
        "close": 7339.79,
        "pct_change": -0.89,
        "volume_fmt": "$1.9B"
      },
      "secondary": {
        "name": "NASDAQ",
        "ticker": "^IXIC",
        "close": 25467.85,
        "pct_change": -1.78,
        "volume_fmt": "$7.9B"
      },
      "tertiary": {
        "name": "Dow Jones",
        "ticker": "^DJI",
        "close": 50726.44,
        "pct_change": -0.12,
        "volume_fmt": "$0.3B"
      },
      "sparkline": [
        7553.68,
        7584.31,
        7383.74,
        7405.73,
        7339.79
      ]
    }
  },
  "sectors": {
    "AI / Chips": {
      "anchor": "SOXX",
      "markets": "US/HK/KR",
      "close": 544.35,
      "pct_change": -4.74
    },
    "CN Internet": {
      "anchor": "KWEB",
      "markets": "HK/CN",
      "close": 26.14,
      "pct_change": 0.06
    },
    "EV / Battery": {
      "anchor": "LIT",
      "markets": "CN/US",
      "close": 77.98,
      "pct_change": 1.15
    },
    "Robotics": {
      "anchor": "ROBO",
      "markets": "JP/CN",
      "close": 82.18,
      "pct_change": -2.55
    },
    "Clean Energy": {
      "anchor": "ICLN",
      "markets": "US/CN",
      "close": 20.49,
      "pct_change": -2.43
    },
    "Biotech": {
      "anchor": "XBI",
      "markets": "US/HK/KR",
      "close": 130.02,
      "pct_change": 1.24
    },
    "Financials": {
      "anchor": "XLF",
      "markets": "US/HK/KR",
      "close": 52.38,
      "pct_change": 0.78
    },
    "Defence": {
      "anchor": "ITA",
      "markets": "US/KR",
      "close": 228.35,
      "pct_change": 0.48
    }
  },
  "fx": {
    "USD/HKD": {
      "rate": 7.84,
      "pct_change": 0.04
    },
    "USD/CNY": {
      "rate": 6.77,
      "pct_change": 0.1
    },
    "USD/KRW": {
      "rate": 1527.8,
      "pct_change": -1.72
    },
    "USD/JPY": {
      "rate": 160.33,
      "pct_change": 0.0
    },
    "EUR/USD": {
      "rate": 1.16,
      "pct_change": 0.27
    },
    "DXY": {
      "rate": 99.89,
      "pct_change": -0.16
    }
  },
  "movers": {
    "HK": {
      "gainers": [],
      "losers": [],
      "is_friday_fallback": false,
      "screener_note": "Last trading day data"
    },
    "US": {
      "gainers": [
        {
          "ticker": "TMO",
          "close": 488.49,
          "pct_change": 4.02,
          "volume": 1000910,
          "volume_fmt": "$1M",
          "longName": "Thermo Fisher Scientific Inc.",
          "industry": "Diagnostics & Research"
        },
        {
          "ticker": "HD",
          "close": 321.23,
          "pct_change": 3.72,
          "volume": 2544513,
          "volume_fmt": "$3M",
          "longName": "The Home Depot, Inc.",
          "industry": "Home Improvement Retail"
        },
        {
          "ticker": "DHR",
          "close": 188.5,
          "pct_change": 2.71,
          "volume": 1553073,
          "volume_fmt": "$2M",
          "longName": "Danaher Corporation",
          "industry": "Diagnostics & Research"
        },
        {
          "ticker": "KO",
          "close": 81.1,
          "pct_change": 1.96,
          "volume": 9829380,
          "volume_fmt": "$10M",
          "longName": "The Coca-Cola Company",
          "industry": "Beverages - Non-Alcoholic"
        },
        {
          "ticker": "AXP",
          "close": 318.29,
          "pct_change": 1.92,
          "volume": 1483505,
          "volume_fmt": "$1M",
          "longName": "American Express Company",
          "industry": "Credit Services"
        }
      ],
      "losers": [
        {
          "ticker": "MRVL",
          "close": 255.27,
          "pct_change": -11.63,
          "volume": 67656659,
          "volume_fmt": "$68M",
          "longName": "Marvell Technology, Inc.",
          "industry": "Semiconductors"
        },
        {
          "ticker": "SMCI",
          "close": 39.75,
          "pct_change": -9.64,
          "volume": 30460296,
          "volume_fmt": "$30M",
          "longName": "Super Micro Computer, Inc.",
          "industry": "Computer Hardware"
        },
        {
          "ticker": "ARM",
          "close": 315.35,
          "pct_change": -8.96,
          "volume": 9592036,
          "volume_fmt": "$10M",
          "longName": "Arm Holdings plc",
          "industry": "Semiconductors"
        },
        {
          "ticker": "QCOM",
          "close": 198.92,
          "pct_change": -8.66,
          "volume": 20922169,
          "volume_fmt": "$21M",
          "longName": "QUALCOMM Incorporated",
          "industry": "Semiconductors"
        },
        {
          "ticker": "NOW",
          "close": 105.87,
          "pct_change": -7.29,
          "volume": 24472572,
          "volume_fmt": "$24M",
          "longName": "ServiceNow, Inc.",
          "industry": "Software - Application"
        }
      ],
      "is_friday_fallback": false,
      "screener_note": "Last trading day data"
    }
  },
  "news": [
    {
      "title": "Prediction: Eli Lilly Will Trade at This Price in a Year",
      "url": "https://247wallst.com/investing/2026/06/09/prediction-eli-lilly-will-trade-at-this-price-in-a-year/?.tsrc=rss",
      "source": "Yahoo! Finance: NVDA News",
      "published_hkt": "2026-06-10 01:33 HKT",
      "label": "Semiconductors"
    },
    {
      "title": "This Ocean Mining Stock Just Got a Green Light From NOAA. Is it a Buy?",
      "url": "https://www.fool.com/investing/2026/06/09/ocean-mining-stock-tmc-green-light-noaa-buy/?.tsrc=rss",
      "source": "Yahoo! Finance: NVDA News",
      "published_hkt": "2026-06-10 01:33 HKT",
      "label": "Semiconductors"
    },
    {
      "title": "Here’s What Analysts Are Saying About Lumentum Holdings (LITE)",
      "url": "https://finance.yahoo.com/markets/stocks/articles/analysts-saying-lumentum-holdings-lite-172440086.html?.tsrc=rss",
      "source": "Yahoo! Finance: NVDA News",
      "published_hkt": "2026-06-10 01:24 HKT",
      "label": "Semiconductors"
    },
    {
      "title": "Is NVIDIA (NVDA) One of the Best NASDAQ Stocks to Buy and Hold for 3 Years?",
      "url": "https://finance.yahoo.com/markets/stocks/articles/nvidia-nvda-one-best-nasdaq-172352123.html?.tsrc=rss",
      "source": "Yahoo! Finance: NVDA News",
      "published_hkt": "2026-06-10 01:23 HKT",
      "label": "Semiconductors"
    },
    {
      "title": "Silver Has Tumbled 46% From its Peak to $66 an Ounce. Is This Top Silver ETF Still a Buy?",
      "url": "https://www.fool.com/investing/2026/06/09/silver-has-tumbled-x-from-its-peak-to-x-an-ounce-i/?.tsrc=rss",
      "source": "Yahoo! Finance: NVDA News",
      "published_hkt": "2026-06-10 01:22 HKT",
      "label": "Semiconductors"
    },
    {
      "title": "Gold is Down 23% from the Peak to $4,330 an Ounce. Time to Buy This Top Gold ETF?",
      "url": "https://www.fool.com/investing/2026/06/09/gold-is-down-x-from-the-peak-to-x-an-ounce-time-to/?.tsrc=rss",
      "source": "Yahoo! Finance: NVDA News",
      "published_hkt": "2026-06-10 01:20 HKT",
      "label": "Semiconductors"
    },
    {
      "title": "Why Apple Stock Is Sinking Today",
      "url": "https://www.fool.com/investing/2026/06/09/why-apple-stock-is-sinking-today/?.tsrc=rss",
      "source": "Yahoo! Finance: ^GSPC News",
      "published_hkt": "2026-06-10 01:18 HKT",
      "label": "US Markets"
    },
    {
      "title": "Nasdaq falls 3% as chip stocks sell off, Iran deal hopes fade",
      "url": "https://qz.com/nasdaq-chip-stocks-selloff-iran-deal-060926?.tsrc=rss",
      "source": "Yahoo! Finance: ^GSPC News",
      "published_hkt": "2026-06-10 01:15 HKT",
      "label": "US Markets"
    },
    {
      "title": "Stock Market Today, June 9: Chipmakers Drag Nasdaq Down at Midday",
      "url": "https://www.fool.com/coverage/stock-market-today/2026/06/09/stock-market-today-june-9-chipmakers-drag-nasdaq-down-at-midday/?.tsrc=rss",
      "source": "Yahoo! Finance: ^GSPC News",
      "published_hkt": "2026-06-10 01:15 HKT",
      "label": "US Markets"
    },
    {
      "title": "S&P 500 and Nasdaq Dips as Chip Stocks Drag Markets Lower",
      "url": "https://finance.yahoo.com/markets/stocks/articles/p-500-nasdaq-dips-chip-170157742.html?.tsrc=rss",
      "source": "Yahoo! Finance: ^GSPC News",
      "published_hkt": "2026-06-10 01:01 HKT",
      "label": "US Markets"
    },
    {
      "title": "Dow Falls Over 500 Points, Nasdaq Sinks As Tech Stocks Tumble — Wells Fargo Warns 'Sugar Rush' Behind Recent Surge Likely Over",
      "url": "https://stocktwits.com/news-articles/markets/equity/dow-falls-nasdaq-sinks-as-tech-stocks-tumble-wells-fargo-warns/cZ0US2wR7Rg?.tsrc=rss",
      "source": "Yahoo! Finance: ^GSPC News",
      "published_hkt": "2026-06-10 00:59 HKT",
      "label": "US Markets"
    },
    {
      "title": "Why Sandisk Stock Is Sinking Today After Being Up 10%",
      "url": "https://www.fool.com/investing/2026/06/09/why-sandisk-stock-is-sinking-today-after-being-up/?.tsrc=rss",
      "source": "Yahoo! Finance: ^GSPC News",
      "published_hkt": "2026-06-10 00:50 HKT",
      "label": "US Markets"
    },
    {
      "title": "Microsoft’s $9K Return on $1K Crushes The Market",
      "url": "https://247wallst.com/investing/2026/06/09/microsofts-9k-return-on-1k-crushes-the-market/?.tsrc=rss",
      "source": "Yahoo! Finance: ^GSPC News",
      "published_hkt": "2026-06-10 00:45 HKT",
      "label": "US Markets"
    },
    {
      "title": "The S&P 500 Just Added This AI Semiconductor Stock For Index Investors",
      "url": "https://www.fool.com/investing/2026/06/09/the-sp-500-just-added-this-ai-semiconductor-stock-for-index-investors/?.tsrc=rss",
      "source": "Yahoo! Finance: ^GSPC News",
      "published_hkt": "2026-06-10 00:43 HKT",
      "label": "US Markets"
    },
    {
      "title": "Alibaba Stock Has Bigger Problems Than the Pentagon’s China List",
      "url": "https://finance.yahoo.com/m/1a5b248e-c49b-3f87-ab08-e39400657e5b/alibaba-stock-has-bigger.html?.tsrc=rss",
      "source": "Yahoo! Finance: 9988.HK News",
      "published_hkt": "2026-06-09 22:15 HKT",
      "label": "China Tech"
    },
    {
      "title": "Investors Heavily Search Alibaba Group Holding Limited (BABA): Here is What You Need to Know",
      "url": "https://finance.yahoo.com/markets/stocks/articles/investors-heavily-search-alibaba-group-130006885.html?.tsrc=rss",
      "source": "Yahoo! Finance: 9988.HK News",
      "published_hkt": "2026-06-09 21:00 HKT",
      "label": "China Tech"
    },
    {
      "title": "美國將阿里巴巴、比亞迪列入「涉軍」清單 中國外交部回應！",
      "url": "https://hk.finance.yahoo.com/news/%E7%BE%8E%E5%9C%8B%E5%B0%87%E9%98%BF%E9%87%8C%E5%B7%B4%E5%B7%B4-%E6%AF%94%E4%BA%9E%E8%BF%AA%E5%88%97%E5%85%A5-%E6%B6%89%E8%BB%8D-%E6%B8%85%E5%96%AE-%E4%B8%AD%E5%9C%8B%E5%A4%96%E4%BA%A4%E9%83%A8%E5%9B%9E%E6%87%89-125754966.html?.tsrc=rss",
      "source": "Yahoo! Finance: 9988.HK News",
      "published_hkt": "2026-06-09 20:57 HKT",
      "label": "China Tech"
    },
    {
      "title": "SpaceX Stock Starts Trading This Week. Here's What to Expect.",
      "url": "https://www.fool.com/investing/2026/06/09/spacex-stock-starts-trading-this-week-heres-what-t/?.tsrc=rss",
      "source": "Yahoo! Finance: 9988.HK News",
      "published_hkt": "2026-06-09 20:05 HKT",
      "label": "China Tech"
    },
    {
      "title": "短炒波士｜港股仍有阻力 宜博小反彈｜Ringo",
      "url": "https://hk.finance.yahoo.com/news/%E7%9F%AD%E7%82%92%E6%B3%A2%E5%A3%AB-%E6%B8%AF%E8%82%A1%E4%BB%8D%E6%9C%89%E9%98%BB%E5%8A%9B-%E5%AE%9C%E5%8D%9A%E5%B0%8F%E5%8F%8D%E5%BD%88-ringo-110000974.html?.tsrc=rss",
      "source": "Yahoo! Finance: ^HSI News",
      "published_hkt": "2026-06-09 19:00 HKT",
      "label": "Asia Markets"
    },
    {
      "title": "港股通盈富基金淨流出114.19億港元",
      "url": "https://hk.finance.yahoo.com/news/%E6%B8%AF%E8%82%A1%E9%80%9A%E7%9B%88%E5%AF%8C%E5%9F%BA%E9%87%91%E6%B7%A8%E6%B5%81%E5%87%BA114-19%E5%84%84%E6%B8%AF%E5%85%83-102501211.html?.tsrc=rss",
      "source": "Yahoo! Finance: 9988.HK News",
      "published_hkt": "2026-06-09 18:25 HKT",
      "label": "China Tech"
    },
    {
      "title": "〈港股盤後〉恒指窄幅震盪跌0.37% 半導體板塊逆勢上漲 科指升0.29%",
      "url": "https://hk.finance.yahoo.com/news/%E6%B8%AF%E8%82%A1%E7%9B%A4%E5%BE%8C-%E6%81%92%E6%8C%87%E7%AA%84%E5%B9%85%E9%9C%87%E7%9B%AA%E8%B7%8C0-37-%E5%8D%8A%E5%B0%8E%E9%AB%94%E6%9D%BF%E5%A1%8A%E9%80%86%E5%8B%A2%E4%B8%8A%E6%BC%B2-%E7%A7%91%E6%8C%87%E5%8D%870-083846770.html?.tsrc=rss",
      "source": "Yahoo! Finance: ^HSI News",
      "published_hkt": "2026-06-09 16:38 HKT",
      "label": "Asia Markets"
    },
    {
      "title": "凱基維持恒指年底目標30000點及住宅樓價升10%預測不變",
      "url": "https://hk.finance.yahoo.com/news/%E5%87%B1%E5%9F%BA%E7%B6%AD%E6%8C%81%E6%81%92%E6%8C%87%E5%B9%B4%E5%BA%95%E7%9B%AE%E6%A8%9930000%E9%BB%9E%E5%8F%8A%E4%BD%8F%E5%AE%85%E6%A8%93%E5%83%B9%E5%8D%8710-%E9%A0%90%E6%B8%AC%E4%B8%8D%E8%AE%8A-083324298.html?.tsrc=rss",
      "source": "Yahoo! Finance: ^HSI News",
      "published_hkt": "2026-06-09 16:33 HKT",
      "label": "Asia Markets"
    },
    {
      "title": "恒指全日收報24565.90點  跌 0.37%  成交3,089.16億元",
      "url": "https://hk.finance.yahoo.com/news/%E6%81%92%E6%8C%87%E5%85%A8%E6%97%A5%E6%94%B6%E5%A0%B124565-90%E9%BB%9E-%E8%B7%8C-0-37-081500028.html?.tsrc=rss",
      "source": "Yahoo! Finance: ^HSI News",
      "published_hkt": "2026-06-09 16:15 HKT",
      "label": "Asia Markets"
    },
    {
      "title": "《全日速報》恆指全日收報24,565點 跌91點; 恆生科技指數全日收報4,769點 升13點 東方海外跌逾5% 中行、建滔、建滔積層板創新高 成交暢旺",
      "url": "https://hk.finance.yahoo.com/news/%E5%85%A8%E6%97%A5%E9%80%9F%E5%A0%B1-%E6%81%86%E6%8C%87%E5%85%A8%E6%97%A5%E6%94%B6%E5%A0%B124-565%E9%BB%9E-%E8%B7%8C91%E9%BB%9E-%E6%81%86%E7%94%9F%E7%A7%91%E6%8A%80%E6%8C%87%E6%95%B8%E5%85%A8%E6%97%A5%E6%94%B6%E5%A0%B14-081230485.html?.tsrc=rss",
      "source": "Yahoo! Finance: ^HSI News",
      "published_hkt": "2026-06-09 16:12 HKT",
      "label": "Asia Markets"
    },
    {
      "title": "《港股》恒指「五連跌」全日跌91點  騰訊升幅收窄至1.5%  建滔系炒高",
      "url": "https://hk.finance.yahoo.com/news/%E6%B8%AF%E8%82%A1-%E6%81%92%E6%8C%87-%E4%BA%94%E9%80%A3%E8%B7%8C-%E5%85%A8%E6%97%A5%E8%B7%8C91%E9%BB%9E-%E9%A8%B0%E8%A8%8A%E5%8D%87%E5%B9%85%E6%94%B6%E7%AA%84%E8%87%B31-080954507.html?.tsrc=rss",
      "source": "Yahoo! Finance: ^HSI News",
      "published_hkt": "2026-06-09 16:09 HKT",
      "label": "Asia Markets"
    },
    {
      "title": "中方促美方停止無理打壓中企",
      "url": "https://hk.finance.yahoo.com/news/%E4%B8%AD%E6%96%B9%E4%BF%83%E7%BE%8E%E6%96%B9%E5%81%9C%E6%AD%A2%E7%84%A1%E7%90%86%E6%89%93%E5%A3%93%E4%B8%AD%E4%BC%81-075924274.html?.tsrc=rss",
      "source": "Yahoo! Finance: 9988.HK News",
      "published_hkt": "2026-06-09 15:59 HKT",
      "label": "China Tech"
    },
    {
      "title": "《港股》恒指半日反覆跌36點 騰訊升逾3% 藥明康德挫5%",
      "url": "https://hk.finance.yahoo.com/news/%E6%B8%AF%E8%82%A1-%E6%81%92%E6%8C%87%E5%8D%8A%E6%97%A5%E5%8F%8D%E8%A6%86%E8%B7%8C36%E9%BB%9E-%E9%A8%B0%E8%A8%8A%E5%8D%87%E9%80%BE3-%E8%97%A5%E6%98%8E%E5%BA%B7%E5%BE%B7%E6%8C%AB5-042355537.html?.tsrc=rss",
      "source": "Yahoo! Finance: ^HSI News",
      "published_hkt": "2026-06-09 12:23 HKT",
      "label": "Asia Markets"
    },
    {
      "title": "恒指半日收報24620.43點  跌 0.15%  成交1,557.08億元",
      "url": "https://hk.finance.yahoo.com/news/%E6%81%92%E6%8C%87%E5%8D%8A%E6%97%A5%E6%94%B6%E5%A0%B124620-43%E9%BB%9E-%E8%B7%8C-0-15-041500637.html?.tsrc=rss",
      "source": "Yahoo! Finance: ^HSI News",
      "published_hkt": "2026-06-09 12:15 HKT",
      "label": "Asia Markets"
    }
  ]
}