{
  "updated": "2026-07-09T17:53:12.251393+00:00",
  "hk": [
    {
      "title": "A World of Opportunity Begins at Canadian International School of Hong Kong",
      "link": "https://www.scmp.com/presented/news/hong-kong/education/topics/ib-diploma-results-2026/article/3359663/world-opportunity-begins-canadian-international-school-hong-kong?utm_source=rss_feed",
      "publishedAt": "Thu, 09 Jul 2026 16:00:07 +0000",
      "source": "SCMP",
      "desc": "[The content of this article has been produced by our advertising partner.]\nChoosing the right school is about more than",
      "badge": "SCMP",
      "color": "var(--gold)"
    },
    {
      "title": "Cathay Pacific aircraft’s tail hit runway at Hong Kong airport, airline confirms",
      "link": "https://www.scmp.com/news/hong-kong/transport/article/3360022/cathay-pacific-aircrafts-tail-hit-runway-hong-kong-airport-airline-confirms?utm_source=rss_feed",
      "publishedAt": "Thu, 09 Jul 2026 13:47:39 +0000",
      "source": "SCMP",
      "desc": "Cathay Pacific Airways has confirmed that the tail of a passenger aircraft struck the runway at Hong Kong airport last w",
      "badge": "SCMP",
      "color": "var(--gold)"
    },
    {
      "title": "Regulator outlines review after Cathay flight intercepted by Nato jets",
      "link": "https://www.scmp.com/news/hong-kong/transport/article/3360023/regulator-outlines-review-after-cathay-flight-intercepted-nato-jets?utm_source=rss_feed",
      "publishedAt": "Thu, 09 Jul 2026 13:43:20 +0000",
      "source": "SCMP",
      "desc": "Hong Kong’s aviation regulator has ordered Cathay Pacific Airways to conduct a comprehensive review of an incident invol",
      "badge": "SCMP",
      "color": "var(--gold)"
    },
    {
      "title": "Pak Shek Kok station on East Rail line scheduled to open as early as 2033",
      "link": "https://www.scmp.com/news/hong-kong/hong-kong-economy/article/3360021/pak-shek-kok-station-east-rail-line-scheduled-open-early-2033?utm_source=rss_feed",
      "publishedAt": "Thu, 09 Jul 2026 13:01:19 +0000",
      "source": "SCMP",
      "desc": "Pak Shek Kok station on the East Rail line is expected to open as early as 2033, Hong Kong authorities have said, unveil",
      "badge": "SCMP",
      "color": "var(--gold)"
    },
    {
      "title": "Parent company of Hong Kong IVF clinic says sorry for embryo specimen mix-up",
      "link": "https://www.scmp.com/news/hong-kong/health-environment/article/3360019/parent-company-hong-kong-ivf-clinic-says-sorry-over-embryo-specimen-mix?utm_source=rss_feed",
      "publishedAt": "Thu, 09 Jul 2026 12:46:44 +0000",
      "source": "SCMP",
      "desc": "The parent group of a Hong Kong fertility clinic involved in a rare mix-up of embryo biopsy specimens has apologised for",
      "badge": "SCMP",
      "color": "var(--gold)"
    }
  ],
  "us": [],
  "earnings": [],
  "eco": [
    {
      "time": "2024-11-26 10:47",
      "country": "US",
      "event": "Deutsche Bank forecasts S&P 500 to hit 7000 by end of 2025",
      "imp": 1,
      "link": "https://www.investing.com/news/stock-market-news/deutsche-bank-forecasts-sp-500-to-hit-7000-by-end-of-2025-3741586",
      "desc": ""
    },
    {
      "time": "2024-11-26 08:55",
      "country": "US",
      "event": "Trump's tariffs, Fed minutes, Rumble's Bitcoin buy - what's moving markets",
      "imp": 1,
      "link": "https://www.investing.com/news/economy/trumps-tariffs-fed-minutes-rumbles-bitcoin-buy--whats-moving-markets-3741453",
      "desc": ""
    },
    {
      "time": "2024-11-26 06:22",
      "country": "US",
      "event": "Bitcoin price today: slips to $94k as risk appetite sours on Trump tariff threat",
      "imp": 1,
      "link": "https://www.investing.com/news/cryptocurrency-news/bitcoin-price-today-slips-to-94k-as-risk-appetite-sours-on-trump-tariff-threat-3741330",
      "desc": ""
    },
    {
      "time": "2024-11-26 08:26",
      "country": "US",
      "event": "2025 macro outlook for the US is 'murky at best' says Deutsche Bank",
      "imp": 1,
      "link": "https://www.investing.com/news/economy/2025-macro-outlook-for-the-us-is-murky-at-best-says-deutsche-bank-3741435",
      "desc": ""
    },
    {
      "time": "2024-11-26 00:01",
      "country": "CN",
      "event": "Trump says he will impose additional 10% tariffs on China over drug inflow",
      "imp": 1,
      "link": "https://www.investing.com/news/politics/trump-says-he-will-impose-additional-10-tariffs-on-china-over-drug-inflow-3741069",
      "desc": ""
    },
    {
      "time": "2024-11-26 03:31",
      "country": "JP",
      "event": "Asia stocks fall after Trump threatens tariffs, Japan's Nikkei leads losses",
      "imp": 1,
      "link": "https://www.investing.com/news/stock-market-news/asia-stocks-fall-after-trump-threatens-tariffs-japans-nikkei-leads-losses-3741249",
      "desc": ""
    },
    {
      "time": "2024-11-26 03:26",
      "country": "US",
      "event": "S&P 500 positioning levels at record highs, pullback risks rise, Citi warns",
      "imp": 1,
      "link": "https://www.investing.com/news/stock-market-news/sp-500-positioning-levels-at-record-highs-pullback-risks-rise-citi-warns-3741245",
      "desc": ""
    },
    {
      "time": "2024-11-25 18:20",
      "country": "US",
      "event": "Analyst calls Bitcoin 'global bubble', could soar to infinity",
      "imp": 1,
      "link": "https://www.investing.com/news/cryptocurrency-news/analyst-calls-bitcoin-global-bubble-could-soar-to-infinity-3740406",
      "desc": ""
    },
    {
      "time": "2024-11-25 21:05",
      "country": "US",
      "event": "Stock market today: Dow hits record as Trump's pick for Treasury stokes optimism",
      "imp": 1,
      "link": "https://www.investing.com/news/stock-market-news/stock-market-today-dow-hits-record-as-trumps-pick-for-treasury-stokes-optimism-3738482",
      "desc": ""
    },
    {
      "time": "2024-11-25 14:19",
      "country": "US",
      "event": "Jump in Tesla stock mostly driven by 'animal spirits/momentum' says UBS",
      "imp": 1,
      "link": "https://www.investing.com/news/stock-market-news/jump-in-tesla-stock-mostly-driven-by-animal-spiritsmomentum-says-ubs-3739718",
      "desc": ""
    }
  ],
  "surprises": [],
  "movers": [
    {
      "symbol": "NVDA",
      "name": "NVIDIA Corporation",
      "price": "203.38",
      "chg": "-0.36%",
      "up": false,
      "label": "ACTIVE",
      "color": "var(--text-muted)"
    },
    {
      "symbol": "AAL",
      "name": "American Airlines Gr",
      "price": "17.33",
      "chg": "+4.90%",
      "up": true,
      "label": "ACTIVE",
      "color": "var(--text-muted)"
    },
    {
      "symbol": "INTC",
      "name": "Intel Corporation",
      "price": "112.78",
      "chg": "+2.30%",
      "up": true,
      "label": "ACTIVE",
      "color": "var(--text-muted)"
    },
    {
      "symbol": "LASR",
      "name": "nLIGHT, Inc.",
      "price": "74.57",
      "chg": "+27.08%",
      "up": true,
      "label": "GAINER",
      "color": "var(--up)"
    },
    {
      "symbol": "LBTYB",
      "name": "Liberty Global Ltd.",
      "price": "13.12",
      "chg": "+19.27%",
      "up": true,
      "label": "GAINER",
      "color": "var(--up)"
    },
    {
      "symbol": "BBIO",
      "name": "BridgeBio Pharma, In",
      "price": "90.81",
      "chg": "+15.93%",
      "up": true,
      "label": "GAINER",
      "color": "var(--up)"
    },
    {
      "symbol": "IONS",
      "name": "Ionis Pharmaceutical",
      "price": "64.48",
      "chg": "-23.65%",
      "up": false,
      "label": "LOSER",
      "color": "var(--down)"
    },
    {
      "symbol": "PLBL",
      "name": "Polibeli Group Ltd",
      "price": "6.16",
      "chg": "-17.56%",
      "up": false,
      "label": "LOSER",
      "color": "var(--down)"
    },
    {
      "symbol": "GVA",
      "name": "Granite Construction",
      "price": "127.61",
      "chg": "-11.08%",
      "up": false,
      "label": "LOSER",
      "color": "var(--down)"
    }
  ]
}